<?xml version="1.0" encoding="UTF-8"?>
<con:soapui-project id="859474e8-b477-4748-832c-8fbe4fc208ac" activeEnvironment="Default" name="REST Project 1" resourceRoot="" soapui-version="5.6.1" abortOnError="false" runType="SEQUENTIAL" xmlns:con="http://eviware.com/soapui/config"><con:settings/><con:interface xsi:type="con:RestService" id="423ea5fe-8012-4cb6-935d-d9fac8eda9f6" wadlVersion="http://wadl.dev.java.net/2009/02" name="http://api.openweathermap.org" type="rest" xmlns:xsi="http://www.w3.org/2001/XMLSchema-instance"><con:settings/><con:definitionCache/><con:endpoints><con:endpoint>http://api.openweathermap.org</con:endpoint></con:endpoints><con:resource name="Direct" path="/geo/1.0/direct" id="1358fa3d-48b1-49c6-a50f-918b81460740"><con:settings/><con:parameters><con:parameter><con:name>q</con:name><con:value>{city name},{state code},{country code}</con:value><con:style>QUERY</con:style><con:default>{city name},{state code},{country code}</con:default><con:path xsi:nil="true"/><con:description xsi:nil="true"/></con:parameter><con:parameter><con:name>limit</con:name><con:value>{limit}</con:value><con:style>QUERY</con:style><con:default>{limit}</con:default><con:path xsi:nil="true"/><con:description xsi:nil="true"/></con:parameter><con:parameter><con:name>appid</con:name><con:value>{API key}</con:value><con:style>QUERY</con:style><con:default>{API key}</con:default><con:path xsi:nil="true"/><con:description xsi:nil="true"/></con:parameter></con:parameters><con:method name="Direct 1" id="e8b3f60a-4fde-4e52-a4b4-7c6f845c0372" method="GET"><con:settings/><con:parameters/><con:representation type="RESPONSE"><con:mediaType>application/json; charset=utf-8</con:mediaType><con:status>200</con:status><con:params/><con:element>Response</con:element></con:representation><con:request name="Request 1" id="3bb20c52-f3f3-4755-8c46-650135be53b5" mediaType="application/json"><con:settings/><con:endpoint>http://api.openweathermap.org</con:endpoint><con:request/><con:credentials><con:authType>No Authorization</con:authType></con:credentials><con:jmsConfig JMSDeliveryMode="PERSISTENT"/><con:jmsPropertyConfig/><con:parameters>
  <con:entry key="q" value="{city name},{state code},{country code}"/>
  <con:entry key="appid" value="{API key}"/>
  <con:entry key="limit" value="{limit}"/>
</con:parameters><con:parameterOrder><con:entry>q</con:entry><con:entry>limit</con:entry><con:entry>appid</con:entry></con:parameterOrder></con:request></con:method></con:resource><con:resource name="DirectAux" path="/geo/1.0/direct" id="1358fa3d-48b1-49c6-a50f-918b81460740"><con:settings/><con:parameters><con:parameter><con:name>q</con:name><con:value>{city name},{state code},{country code}</con:value><con:style>QUERY</con:style><con:default>{city name},{state code},{country code}</con:default><con:path xsi:nil="true"/><con:description xsi:nil="true"/></con:parameter><con:parameter><con:name>limit</con:name><con:value>{limit}</con:value><con:style>QUERY</con:style><con:default>{limit}</con:default><con:path xsi:nil="true"/><con:description xsi:nil="true"/></con:parameter><con:parameter><con:name>appid</con:name><con:value>{API key}</con:value><con:style>QUERY</con:style><con:default>{API key}</con:default><con:path xsi:nil="true"/><con:description xsi:nil="true"/></con:parameter></con:parameters><con:method name="Direct 1" id="e8b3f60a-4fde-4e52-a4b4-7c6f845c0372" method="GET"><con:settings/><con:parameters/><con:representation type="RESPONSE"><con:mediaType>application/json; charset=utf-8</con:mediaType><con:status>200</con:status><con:params/><con:element>Response</con:element></con:representation><con:request name="Request 1" id="3bb20c52-f3f3-4755-8c46-650135be53b5" mediaType="application/json"><con:settings><con:setting id="com.eviware.soapui.impl.wsdl.WsdlRequest@request-headers">&lt;xml-fragment/></con:setting></con:settings><con:endpoint>http://api.openweathermap.org</con:endpoint><con:request/><con:originalUri>http://api.openweathermap.org/geo/1.0/direct</con:originalUri><con:credentials><con:authType>No Authorization</con:authType></con:credentials><con:jmsConfig JMSDeliveryMode="PERSISTENT"/><con:jmsPropertyConfig/><con:parameters>
  <con:entry key="q" value="London"/>
  <con:entry key="appid" value="fbd927b11b294b987bd3bc3bb789703f"/>
  <con:entry key="limit" value="5"/>
</con:parameters><con:parameterOrder><con:entry>q</con:entry><con:entry>limit</con:entry><con:entry>appid</con:entry></con:parameterOrder></con:request></con:method></con:resource></con:interface><con:interface xsi:type="con:RestService" id="b26ca81a-6677-488a-9dc1-6d331eeffb94" wadlVersion="http://wadl.dev.java.net/2009/02" name="https://api.openweathermap.org" type="rest" xmlns:xsi="http://www.w3.org/2001/XMLSchema-instance"><con:settings/><con:definitionCache/><con:endpoints><con:endpoint>https://api.openweathermap.org</con:endpoint></con:endpoints><con:resource name="Weather" path="/data/2.5/weather" id="6784b8d3-4e78-4e91-b427-1107a1cff470"><con:settings/><con:parameters><con:parameter><con:name>lat</con:name><con:value>35</con:value><con:style>QUERY</con:style><con:default>35</con:default><con:path xsi:nil="true"/><con:description xsi:nil="true"/></con:parameter><con:parameter><con:name>lon</con:name><con:value>139</con:value><con:style>QUERY</con:style><con:default>139</con:default><con:path xsi:nil="true"/><con:description xsi:nil="true"/></con:parameter><con:parameter><con:name>appid</con:name><con:value>{API key}</con:value><con:style>QUERY</con:style><con:default>{API key}</con:default><con:path xsi:nil="true"/><con:description xsi:nil="true"/></con:parameter></con:parameters><con:method name="Weather 1" id="6ebefa4b-98d2-4e42-938a-026f2d7dc098" method="GET"><con:settings/><con:parameters/><con:representation type="RESPONSE"><con:mediaType>application/json; charset=utf-8</con:mediaType><con:status>200</con:status><con:params/><con:element xmlns:weat="https://api.openweathermap.org/data/2.5/weather">weat:Response</con:element></con:representation><con:request name="Request 1" id="058b2372-beb3-4ba4-aa80-101a1a45050e" mediaType="application/json"><con:settings/><con:endpoint>https://api.openweathermap.org</con:endpoint><con:request/><con:credentials><con:authType>No Authorization</con:authType></con:credentials><con:jmsConfig JMSDeliveryMode="PERSISTENT"/><con:jmsPropertyConfig/><con:parameters>
  <con:entry key="appid" value="{API key}"/>
  <con:entry key="lon" value="139"/>
  <con:entry key="lat" value="35"/>
</con:parameters><con:parameterOrder><con:entry>lat</con:entry><con:entry>lon</con:entry><con:entry>appid</con:entry></con:parameterOrder></con:request></con:method></con:resource></con:interface><con:testSuite id="5e648b7a-8e30-4f63-8b04-bcc4c4d7b906" name="TestSuite 1"><con:settings/><con:runType>SEQUENTIAL</con:runType><con:testCase id="bd07c7b0-501a-429f-ae8b-71dbfe21854e" failOnError="true" failTestCaseOnErrors="true" keepSession="false" maxResults="0" name="TestCase 1" searchProperties="true"><con:settings/><con:testStep type="properties" name="ParametrosDeEntrada" id="2535e073-474b-45c7-9217-4c56146970db"><con:settings/><con:config xsi:type="con:PropertiesStep" saveFirst="true" xmlns:xsi="http://www.w3.org/2001/XMLSchema-instance"><con:properties><con:property><con:name>//         PARAMETROS DE ENTRADA</con:name><con:value>***********************</con:value></con:property><con:property><con:name>Ciudad</con:name><con:value>Madrid</con:value></con:property><con:property><con:name>Limite</con:name><con:value>5</con:value></con:property><con:property><con:name>ApiKey</con:name><con:value>fbd927b11b294b987bd3bc3bb789703f</con:value></con:property></con:properties></con:config></con:testStep><con:testStep type="transfer" name="Property Transfer 01" id="5316766a-824e-4fc3-9ea7-4ace2aaeefbf"><con:settings/><con:config xsi:type="con:PropertyTransfersStep" xmlns:xsi="http://www.w3.org/2001/XMLSchema-instance"><con:transfers setNullOnMissingSource="true" transferTextContent="true" failOnError="true" ignoreEmpty="false" transferToAll="false" entitize="false" transferChildNodes="false"><con:name>SetCiudad</con:name><con:sourceType>Ciudad</con:sourceType><con:sourceStep>ParametrosDeEntrada</con:sourceStep><con:targetType>q</con:targetType><con:targetStep>GeocodingData</con:targetStep><con:upgraded>true</con:upgraded></con:transfers><con:transfers setNullOnMissingSource="true" transferTextContent="true" failOnError="true" ignoreEmpty="false" transferToAll="false" entitize="false" transferChildNodes="false"><con:name>SetLimit</con:name><con:sourceType>Limite</con:sourceType><con:sourceStep>ParametrosDeEntrada</con:sourceStep><con:targetType>limit</con:targetType><con:targetStep>GeocodingData</con:targetStep><con:upgraded>true</con:upgraded></con:transfers><con:transfers setNullOnMissingSource="true" transferTextContent="true" failOnError="true" ignoreEmpty="false" transferToAll="false" entitize="false" transferChildNodes="false"><con:name>SetApiKey</con:name><con:sourceType>ApiKey</con:sourceType><con:sourceStep>ParametrosDeEntrada</con:sourceStep><con:targetType>appid</con:targetType><con:targetStep>GeocodingData</con:targetStep><con:upgraded>true</con:upgraded></con:transfers></con:config></con:testStep><con:testStep type="restrequest" name="GeocodingData" id="30559a58-a89b-4334-a389-48e9605d90da"><con:settings/><con:config service="http://api.openweathermap.org" resourcePath="/geo/1.0/direct" methodName="Direct 1" xsi:type="con:RestRequestStep" xmlns:xsi="http://www.w3.org/2001/XMLSchema-instance"><con:restRequest name="Step01" id="3bb20c52-f3f3-4755-8c46-650135be53b5" mediaType="application/json"><con:settings><con:setting id="com.eviware.soapui.impl.wsdl.WsdlRequest@request-headers">&lt;xml-fragment/></con:setting></con:settings><con:endpoint>http://api.openweathermap.org</con:endpoint><con:request/><con:originalUri>http://api.openweathermap.org/geo/1.0/direct</con:originalUri><con:credentials><con:authType>No Authorization</con:authType></con:credentials><con:jmsConfig JMSDeliveryMode="PERSISTENT"/><con:jmsPropertyConfig/><con:parameters>
  <con:entry key="q" value="Madrid"/>
  <con:entry key="appid" value="fbd927b11b294b987bd3bc3bb789703f"/>
  <con:entry key="limit" value="5"/>
</con:parameters><con:parameterOrder><con:entry>q</con:entry><con:entry>limit</con:entry><con:entry>appid</con:entry></con:parameterOrder></con:restRequest></con:config></con:testStep><con:testStep type="transfer" name="Property Transfer 02" id="0788bc13-4436-4919-b103-7f9b1a7fb9ab"><con:settings/><con:config xsi:type="con:PropertyTransfersStep" xmlns:xsi="http://www.w3.org/2001/XMLSchema-instance"><con:transfers setNullOnMissingSource="true" transferTextContent="true" failOnError="true" ignoreEmpty="false" transferToAll="false" entitize="false" transferChildNodes="false"><con:name>Get Ciudad</con:name><con:sourceType>Response</con:sourceType><con:sourceStep>GeocodingData</con:sourceStep><con:sourcePath>[0].local_names.es</con:sourcePath><con:targetType>q</con:targetType><con:targetStep>GeocodingData</con:targetStep><con:type>JSONPATH</con:type><con:targetTransferType>XPATH</con:targetTransferType><con:upgraded>true</con:upgraded></con:transfers><con:transfers setNullOnMissingSource="true" transferTextContent="true" failOnError="true" ignoreEmpty="false" transferToAll="false" entitize="false" transferChildNodes="false"><con:name>Get Lon</con:name><con:sourceType>Response</con:sourceType><con:sourceStep>GeocodingData</con:sourceStep><con:sourcePath>[0].lon</con:sourcePath><con:targetType>lon</con:targetType><con:targetStep>WeatherData</con:targetStep><con:type>JSONPATH</con:type><con:upgraded>true</con:upgraded></con:transfers><con:transfers setNullOnMissingSource="true" transferTextContent="true" failOnError="true" ignoreEmpty="false" transferToAll="false" entitize="false" transferChildNodes="false"><con:name>Get Lat</con:name><con:sourceType>Response</con:sourceType><con:sourceStep>GeocodingData</con:sourceStep><con:sourcePath>[0].lat</con:sourcePath><con:targetType>lat</con:targetType><con:targetStep>WeatherData</con:targetStep><con:type>JSONPATH</con:type><con:upgraded>true</con:upgraded></con:transfers><con:transfers setNullOnMissingSource="true" transferTextContent="true" failOnError="true" ignoreEmpty="false" transferToAll="false" entitize="false" transferChildNodes="false"><con:name>Get Ciudad</con:name><con:sourceType>Response</con:sourceType><con:sourceStep>GeocodingData</con:sourceStep><con:sourcePath>[0].local_names.es</con:sourcePath><con:targetType>Ciudad</con:targetType><con:targetStep>Results</con:targetStep><con:type>JSONPATH</con:type><con:upgraded>true</con:upgraded></con:transfers></con:config></con:testStep><con:testStep type="restrequest" name="WeatherData" id="1ca5b8d7-26a1-4660-892f-2f50ccb7f191"><con:settings/><con:config service="https://api.openweathermap.org" resourcePath="/data/2.5/weather" methodName="Weather 1" xsi:type="con:RestRequestStep" xmlns:xsi="http://www.w3.org/2001/XMLSchema-instance"><con:restRequest name="Weather 1 - Request 1" id="058b2372-beb3-4ba4-aa80-101a1a45050e" mediaType="application/json"><con:settings><con:setting id="com.eviware.soapui.impl.wsdl.WsdlRequest@request-headers">&lt;xml-fragment/></con:setting></con:settings><con:endpoint>https://api.openweathermap.org</con:endpoint><con:request/><con:originalUri>https://api.openweathermap.org/data/2.5/weather</con:originalUri><con:credentials><con:authType>No Authorization</con:authType></con:credentials><con:jmsConfig JMSDeliveryMode="PERSISTENT"/><con:jmsPropertyConfig/><con:parameters>
  <con:entry key="appid" value="fbd927b11b294b987bd3bc3bb789703f"/>
  <con:entry key="lon" value="-3.7035825"/>
  <con:entry key="lat" value="40.4167047"/>
</con:parameters><con:parameterOrder><con:entry>lat</con:entry><con:entry>lon</con:entry><con:entry>appid</con:entry></con:parameterOrder></con:restRequest></con:config></con:testStep><con:testStep type="transfer" name="GettingResults" id="57990aae-d24c-43f0-9107-d318dd815a2b"><con:settings/><con:config xsi:type="con:PropertyTransfersStep" xmlns:xsi="http://www.w3.org/2001/XMLSchema-instance"><con:transfers setNullOnMissingSource="true" transferTextContent="true" failOnError="true" ignoreEmpty="false" transferToAll="false" entitize="false" transferChildNodes="false"><con:name>GetTemp</con:name><con:sourceType>Response</con:sourceType><con:sourceStep>WeatherData</con:sourceStep><con:sourcePath>main.temp</con:sourcePath><con:targetType>Temp</con:targetType><con:targetStep>Results</con:targetStep><con:type>JSONPATH</con:type><con:upgraded>true</con:upgraded></con:transfers></con:config></con:testStep><con:testStep type="properties" name="Results" id="494a9231-9a3c-4217-845d-8487dffd559d"><con:settings/><con:config xsi:type="con:PropertiesStep" saveFirst="true" xmlns:xsi="http://www.w3.org/2001/XMLSchema-instance"><con:properties><con:property><con:name>//SOLUCION</con:name><con:value>*************</con:value></con:property><con:property><con:name>Ciudad</con:name><con:value>Madrid</con:value></con:property><con:property><con:name>Temp</con:name><con:value>294.94</con:value></con:property></con:properties></con:config></con:testStep><con:properties><con:property><con:name>Ciudad</con:name><con:value>Madrid</con:value></con:property></con:properties></con:testCase><con:properties><con:property><con:name>Ciudad</con:name><con:value>Madrid</con:value></con:property></con:properties></con:testSuite><con:properties><con:property><con:name>Ciudad</con:name><con:value>Madrid</con:value></con:property></con:properties><con:wssContainer/><con:oAuth2ProfileContainer/><con:oAuth1ProfileContainer/><con:sensitiveInformation/></con:soapui-project>